{
  "id": "TASK-15",
  "title": "Frontend: Formula Editor Popup Component",
  "description": "Build a popup formula editor with human-readable expression input. Variable insertion from current collection (question values, formula results). Operator buttons (+, -, *, /, &&, ||, ?: ternary). Real-time syntax validation with error display. Output type display. JSON AST generation on save.",
  "status": "Approved",
  "creationDate": "2026-06-11T12:53:17.838Z",
  "updateDate": "2026-06-22T07:49:46.525Z",
  "statusHistory": [
    {
      "fromStatus": null,
      "toStatus": "Draft",
      "changedBy": "unknown",
      "changedAt": "2026-06-11T12:53:17.838Z",
      "comment": "Initial creation"
    },
    {
      "fromStatus": "Draft",
      "toStatus": "Plan-ready",
      "changedBy": "planner-agent",
      "changedAt": "2026-06-17T16:45:13.203Z",
      "comment": "Planning completed for TASK-15 - see plan document"
    },
    {
      "fromStatus": "Plan-ready",
      "toStatus": "Ready-to-review",
      "changedBy": "planner-agent",
      "changedAt": "2026-06-17T17:02:00.893Z",
      "comment": "Implementation complete. All components built: FormulaEditorPopup, FormulaList, astConverter, API proxy routes, backend wiring, integrations into FormForm/SectionForm/QuestionForm. Build passes, code review completed."
    },
    {
      "fromStatus": "Ready-to-review",
      "toStatus": "Approved",
      "changedBy": "Pauli Parkkinen",
      "changedAt": "2026-06-22T07:49:46.524Z",
      "approvedBy": "Pauli Parkkinen",
      "approvedAt": "2026-06-22T07:49:46.525Z"
    }
  ],
  "changeHistory": [
    {
      "field": "linkedFeatures",
      "oldValue": [
        "FEAT-1"
      ],
      "newValue": [],
      "changedBy": "planner-agent",
      "changedAt": "2026-06-11T12:53:46.781Z",
      "mode": "remove",
      "item": "FEAT-1"
    },
    {
      "field": "linkedFeatures",
      "oldValue": [],
      "newValue": [
        "FEAT-2"
      ],
      "changedBy": "planner-agent",
      "changedAt": "2026-06-11T12:53:56.289Z",
      "mode": "add",
      "item": "FEAT-2"
    }
  ],
  "significance": "patch",
  "linkedFeatures": [
    "FEAT-2"
  ]
}
